Metadata-Version: 2.1
Name: bitorch-engine
Version: 0.1.0
Summary: A package for building and training quantized and binary neural networks with Pytorch
Home-page: https://github.com/hpi-xnor/bitorch-inference-engine
Author: Hasso Plattner Institute
Author-email: fb10-xnor@hpi.de
Classifier: Development Status :: 3 - Alpha
Classifier: Intended Audience :: Developers
Classifier: License :: OSI Approved :: GNU General Public License v3 or later (GPLv3+)
Classifier: Operating System :: OS Independent
Classifier: Programming Language :: Python :: 3 :: Only
Classifier: Programming Language :: Python :: 3.7
Requires-Python: >=3.7
Provides-Extra: dev
